{
  "taskId": "bloom-marketing-stack",
  "taskName": "Build & Deploy BLOOM Marketing Stack — 10 Universal Skills",
  "progress": 100,
  "lastAction": "Moved all 10 skills to /data/skills (OpenClaw auto-load)",
  "context": {
    "skillsDeployed": 10,
    "skillsReady": 10,
    "deploymentPath": "/data/skills",
    "skills": [
      "viral-hook-generator",
      "dm-sales-engine",
      "story-arc-builder",
      "landing-page-optimizer",
      "trend-hijacker",
      "audience-psychographer",
      "product-launch-sequencer",
      "content-repurposer",
      "testimonial-amplifier",
      "competitor-decoder"
    ]
  },
  "nextStep": "TEST: Use each skill on real client examples",
  "blockers": null,
  "savedAt": "2026-02-19T08:37:52.540Z",
  "priority": "high"
}