{
  "taskId": "bloom-marketing-stack",
  "taskName": "BLOOM Marketing Stack - Complete Deployment",
  "progress": 100,
  "lastAction": "Defined identity, soul, and long-term memory. 10 skills deployed to /data/skills/",
  "context": {
    "skillsDeployed": 10,
    "skillsReady": 10,
    "identityStatus": "DEFINED",
    "soulStatus": "DEFINED",
    "memoryStatus": "ESTABLISHED",
    "valueDelivered": "$25k/month equivalent per Bloomie",
    "deploymentPath": "/data/skills",
    "checkpointSystemActive": true
  },
  "nextStep": "READY FOR PRODUCTION: Test skills on real clients, iterate on feedback",
  "blockers": null,
  "savedAt": "2026-02-19T08:45:46.538Z",
  "priority": "high"
}